{
  "metadata": {
    "title": "Learn FB15k Data Set with R-GCN as described by Schlichtkrull et al., 2018",
    "comments": ""
  },
  "pipeline": {
    "dataset": "fb15k",
    "model": "R-GCN",
    "model_kwargs": {
      "embedding_dim": 500,
      "num_bases_or_blocks": 100,
      "decomposition": "block"
    },
    "optimizer": "Adagrad",
    "optimizer_kwargs": {
      "lr": 0.1
    },
    "loss": "SoftplusLoss",
    "loss_kwargs": {
      "reduction": "mean"
    },
    "training_loop": "SLCWA",
    "negative_sampler": "basic",
    "negative_sampler_kwargs": {
      "num_negs_per_pos": 10
    },
    "training_kwargs": {
      "num_epochs": 500,
      "batch_size": 30000,
      "sub_batch_size": 800
    },
    "evaluator_kwargs": {
      "filtered": true
    }
  }
}